opihiexarata/__init__.py
opihiexarata/__main__.py
opihiexarata/__version__.py
opihiexarata/configuration.yaml
opihiexarata/secrets.yaml
opihiexarata/astrometry/__init__.py
opihiexarata/astrometry/solution.py
opihiexarata/astrometry/webclient.py
opihiexarata/ephemeris/__init__.py
opihiexarata/ephemeris/jplhorizons.py
opihiexarata/ephemeris/solution.py
opihiexarata/gui/__init__.py
opihiexarata/gui/automatic.py
opihiexarata/gui/functions.py
opihiexarata/gui/manual.py
opihiexarata/gui/name.py
opihiexarata/gui/selector.py
opihiexarata/gui/qtui/__init__.py
opihiexarata/gui/qtui/automatic.ui
opihiexarata/gui/qtui/build_qtui_window.ps1
opihiexarata/gui/qtui/busy_image_pyukumuku.png
opihiexarata/gui/qtui/busy_image_pyukumuku_1of4.png
opihiexarata/gui/qtui/busy_image_pyukumuku_2of4.png
opihiexarata/gui/qtui/busy_image_pyukumuku_3of4.png
opihiexarata/gui/qtui/busy_image_pyukumuku_4of4.png
opihiexarata/gui/qtui/manual.ui
opihiexarata/gui/qtui/old_manual.ui
opihiexarata/gui/qtui/qtui_automatic.py
opihiexarata/gui/qtui/qtui_manual.py
opihiexarata/gui/qtui/qtui_selector.py
opihiexarata/gui/qtui/selector.ui
opihiexarata/gui/qtui/window_icon.png
opihiexarata/library/__init__.py
opihiexarata/library/config.py
opihiexarata/library/conversion.py
opihiexarata/library/engine.py
opihiexarata/library/error.py
opihiexarata/library/fits.py
opihiexarata/library/hint.py
opihiexarata/library/http.py
opihiexarata/library/image.py
opihiexarata/library/json.py
opihiexarata/library/mpcrecord.py
opihiexarata/library/path.py
opihiexarata/library/phototable.py
opihiexarata/library/tcs.py
opihiexarata/library/temporary.py
opihiexarata/opihi/__init__.py
opihiexarata/opihi/database.py
opihiexarata/opihi/preprocess.py
opihiexarata/opihi/solution.py
opihiexarata/orbit/__init__.py
opihiexarata/orbit/custom.py
opihiexarata/orbit/orbfit.py
opihiexarata/orbit/solution.py
opihiexarata/photometry/__init__.py
opihiexarata/photometry/panstarrs.py
opihiexarata/photometry/solution.py
opihiexarata-2024.7.1.dist-info/METADATA
opihiexarata-2024.7.1.dist-info/WHEEL
opihiexarata-2024.7.1.dist-info/entry_points.txt
opihiexarata-2024.7.1.dist-info/licenses/LICENSE
opihiexarata-2024.7.1.dist-info/RECORD
