Metadata-Version: 2.4
Name: OpihiExarata
Version: 2024.7.1
Summary: Analysis software for the IRTF Opihi telescope.
Project-URL: Homepage, http://irtfweb.ifa.hawaii.edu/~opihi/
Project-URL: Documentation, https://psmd-iberutaru.github.io/OpihiExarata
Project-URL: Issues, https://github.com/psmd-iberutaru/OpihiExarata/issues
Project-URL: Source, https://github.com/psmd-iberutaru/OpihiExarata/
Author-email: Sparrow <psmd.iberutaru@gmail.com>
License-Expression: MIT
License-File: LICENSE
Classifier: Development Status :: 2 - Pre-Alpha
Classifier: Programming Language :: Python
Classifier: Programming Language :: Python :: 3.9
Classifier: Programming Language :: Python :: Implementation :: CPython
Classifier: Programming Language :: Python :: Implementation :: PyPy
Requires-Python: >=3.9
Requires-Dist: astropy
Requires-Dist: matplotlib
Requires-Dist: numpy
Requires-Dist: pandas
Requires-Dist: pillow
Requires-Dist: plotly
Requires-Dist: pyside6
Requires-Dist: pyyaml
Requires-Dist: requests
Requires-Dist: scikit-image
Requires-Dist: scipy
